cli_example/__init__.py
cli_example/main.py
cli_example-0.3.0.dist-info/licenses/LICENSE
cli_example-0.3.0.dist-info/METADATA
cli_example-0.3.0.dist-info/WHEEL
cli_example-0.3.0.dist-info/entry_points.txt
cli_example-0.3.0.dist-info/top_level.txt
cli_example-0.3.0.dist-info/RECORD
